{
  "trainingPhrases": [ {
    "parts": [ {
      "text": "TUE",
      "auto": true
    } ],
    "repeatCount": 1,
    "languageCode": "en"
  }, {
    "parts": [ {
      "text": "tuesday",
      "auto": true
    } ],
    "repeatCount": 1,
    "languageCode": "en"
  }, {
    "parts": [ {
      "text": "Tue",
      "auto": true
    } ],
    "repeatCount": 1,
    "languageCode": "en"
  }, {
    "parts": [ {
      "text": "tue",
      "auto": true
    } ],
    "repeatCount": 1,
    "languageCode": "en"
  }, {
    "parts": [ {
      "text": "TUESDAY",
      "auto": true
    } ],
    "repeatCount": 1,
    "languageCode": "en"
  }, {
    "parts": [ {
      "text": "Tuesday",
      "auto": true
    } ],
    "repeatCount": 1,
    "languageCode": "en"
  } ]
}
