{
  "entities": [ {
    "value": "^\\d{3}[-\\s]?\\d{3}[-\\s]?\\d{4}$",
    "synonyms": [ "^\\d{3}[-\\s]?\\d{3}[-\\s]?\\d{4}$" ],
    "languageCode": "en"
  }, {
    "value": "^[0-9]{10}$",
    "synonyms": [ "^[0-9]{10}$" ],
    "languageCode": "en"
  }, {
    "value": "^\\d{3}#?$",
    "synonyms": [ "^\\d{3}#?$" ],
    "languageCode": "en"
  }, {
    "value": "^(?:\\+1)?\\s*(?:\\(\\s*(\\d{3})\\s*\\)|\\d{3})[\\s\\-]*(\\d{3})[\\s\\-]*(\\d{4})$",
    "synonyms": [ "^(?:\\+1)?\\s*(?:\\(\\s*(\\d{3})\\s*\\)|\\d{3})[\\s\\-]*(\\d{3})[\\s\\-]*(\\d{4})$" ],
    "languageCode": "en"
  }, {
    "value": "^(?:1)?\\s*(?:\\(\\s*(\\d{3})\\s*\\)|\\d{3})[\\s\\-]*(\\d{3})[\\s\\-]*(\\d{4})$",
    "synonyms": [ "^(?:1)?\\s*(?:\\(\\s*(\\d{3})\\s*\\)|\\d{3})[\\s\\-]*(\\d{3})[\\s\\-]*(\\d{4})$" ],
    "languageCode": "en"
  } ]
}
